embed_video/__init__.py
embed_video/admin.py
embed_video/backends.py
embed_video/fields.py
embed_video/settings.py
embed_video/templates/embed_video/embed_code.html
embed_video/templatetags/__init__.py
embed_video/templatetags/embed_video_tags.py
embed_video/tests/__init__.py
embed_video/tests/django_settings.py
embed_video/tests/tests_admin.py
embed_video/tests/tests_fields.py
embed_video/tests/backends/__init__.py
embed_video/tests/backends/tests_custom_backend.py
embed_video/tests/backends/tests_soundcloud.py
embed_video/tests/backends/tests_videobackend.py
embed_video/tests/backends/tests_vimeo.py
embed_video/tests/backends/tests_youtube.py
embed_video/tests/templatetags/__init__.py
embed_video/tests/templatetags/tests_embed_video_tags.py
django_embed_video-1.4.10.dist-info/LICENSE
django_embed_video-1.4.10.dist-info/METADATA
django_embed_video-1.4.10.dist-info/WHEEL
django_embed_video-1.4.10.dist-info/top_level.txt
django_embed_video-1.4.10.dist-info/RECORD
