Metadata-Version: 2.1
Name: django-embed-video
Version: 1.4.10
Summary: Django app for easy embedding YouTube and Vimeo videos and music from SoundCloud.
Home-page: https://github.com/jazzband/django-embed-video
Author: Cedric Carrard
Author-email: cedric.carrard@gmail.com
Keywords: youtube,vimeo,video,soundcloud
Classifier: Development Status :: 5 - Production/Stable
Classifier: Environment :: Web Environment
Classifier: Environment :: Plugins
Classifier: Framework :: Django
Classifier: Framework :: Django :: 3.2
Classifier: Framework :: Django :: 4.1
Classifier: Framework :: Django :: 4.2
Classifier: Framework :: Django :: 5.0
Classifier: Intended Audience :: Developers
Classifier: License :: OSI Approved :: MIT License
Classifier: Programming Language :: Python
Classifier: Programming Language :: Python :: 3
Classifier: Programming Language :: Python :: 3.8
Classifier: Programming Language :: Python :: 3.9
Classifier: Programming Language :: Python :: 3.10
Classifier: Programming Language :: Python :: 3.11
Classifier: Programming Language :: Python :: 3.12
Classifier: Programming Language :: Python :: Implementation :: CPython
Classifier: Topic :: Internet :: WWW/HTTP
License-File: LICENSE
Requires-Dist: requests>=2.19
Requires-Dist: Django>=3.2
Requires-Dist: importlib-metadata; python_version < "3.8"
